my_app/__init__.py
my_app/my_app.py
test_package_trail_1-0.3.dist-info/METADATA
test_package_trail_1-0.3.dist-info/WHEEL
test_package_trail_1-0.3.dist-info/entry_points.txt
test_package_trail_1-0.3.dist-info/top_level.txt
test_package_trail_1-0.3.dist-info/RECORD
