Metadata-Version: 2.1
Name: test-package-trail-1
Version: 0.3
Requires-Dist: click
